easy_local_features/__init__.py
easy_local_features/py.typed
easy_local_features/datasets/__init__.py
easy_local_features/datasets/augmentor.py
easy_local_features/datasets/download.py
easy_local_features/datasets/megadepth.py
easy_local_features/datasets/scannet.py
easy_local_features/depth/__init__.py
easy_local_features/depth/baseline_depthanythingv2.py
easy_local_features/eval/__init__.py
easy_local_features/eval/pose_eval.py
easy_local_features/eval/pose_table.py
easy_local_features/eval/semantic/__init__.py
easy_local_features/eval/semantic/spair.py
easy_local_features/feature/__init__.py
easy_local_features/feature/baseline_alike.py
easy_local_features/feature/baseline_aliked.py
easy_local_features/feature/baseline_croco.py
easy_local_features/feature/baseline_d2net.py
easy_local_features/feature/baseline_dad.py
easy_local_features/feature/baseline_dalf.py
easy_local_features/feature/baseline_deal.py
easy_local_features/feature/baseline_dedode.py
easy_local_features/feature/baseline_delf.py
easy_local_features/feature/baseline_desc_reasoning.py
easy_local_features/feature/baseline_dinov2.py
easy_local_features/feature/baseline_dinov3.py
easy_local_features/feature/baseline_disk.py
easy_local_features/feature/baseline_logpolar.py
easy_local_features/feature/baseline_mum.py
easy_local_features/feature/baseline_orb.py
easy_local_features/feature/baseline_r2d2.py
easy_local_features/feature/baseline_rekd.py
easy_local_features/feature/baseline_relf.py
easy_local_features/feature/baseline_resnet.py
easy_local_features/feature/baseline_roma.py
easy_local_features/feature/baseline_romav2.py
easy_local_features/feature/baseline_sfd2.py
easy_local_features/feature/baseline_sosnet.py
easy_local_features/feature/baseline_superpoint.py
easy_local_features/feature/baseline_superpoint_open.py
easy_local_features/feature/baseline_tfeat.py
easy_local_features/feature/baseline_topicfm.py
easy_local_features/feature/baseline_vgg.py
easy_local_features-0.8.21.dist-info/METADATA
easy_local_features-0.8.21.dist-info/WHEEL
easy_local_features-0.8.21.dist-info/entry_points.txt
easy_local_features-0.8.21.dist-info/licenses/LICENSES.md
easy_local_features-0.8.21.dist-info/RECORD
