Metadata-Version: 2.4
Name: easy-local-features
Version: 0.8.21
Summary: Add your description here
Author-email: Felipe Cadar <cadar@dcc.ufmg.br>
License-File: LICENSES.md
Requires-Python: >=3.10
Requires-Dist: e2cnn>=0.2.3
Requires-Dist: easydict
Requires-Dist: einops
Requires-Dist: kornia-moons>=0.2.9
Requires-Dist: kornia-rs>=0.1.9
Requires-Dist: loguru==0.6.0
Requires-Dist: numpy
Requires-Dist: omegaconf
Requires-Dist: opencv-python
Requires-Dist: romav2>=2.0.0
Requires-Dist: scikit-image>=0.24.0
Requires-Dist: scipy
Requires-Dist: tensorflow
Requires-Dist: tensorflow-hub
Requires-Dist: timm>=0.9
Requires-Dist: torch
Requires-Dist: torchvision
Requires-Dist: tqdm
Requires-Dist: wget
Requires-Dist: yacs
